turtex.py
turtex-0.0.3.dist-info/LICENSE.txt
turtex-0.0.3.dist-info/METADATA
turtex-0.0.3.dist-info/WHEEL
turtex-0.0.3.dist-info/top_level.txt
turtex-0.0.3.dist-info/RECORD
